sparc/convert/__init__.py
sparc/convert/application.py
sparc_converter-0.3.2.dist-info/LICENSE
sparc_converter-0.3.2.dist-info/METADATA
sparc_converter-0.3.2.dist-info/WHEEL
sparc_converter-0.3.2.dist-info/entry_points.txt
sparc_converter-0.3.2.dist-info/top_level.txt
sparc_converter-0.3.2.dist-info/RECORD
