Metadata-Version: 2.1
Name: sparc-converter
Version: 0.3.2
Summary: Applications to convert SPARC data.
Home-page: https://github.com/hsorby/sparc-converter.git
Author: Hugh Sorby
Author-email: h.sorby@auckland.ac.nz
License: Apache Software License
License-File: LICENSE
Requires-Dist: cmlibs.exporter >=0.2.1
